onlinejudge_command/__0_workaround_for_conflict.py
onlinejudge_command/__about__.py
onlinejudge_command/__init__.py
onlinejudge_command/download_history.py
onlinejudge_command/format_utils.py
onlinejudge_command/log_formatter.py
onlinejudge_command/main.py
onlinejudge_command/output_comparators.py
onlinejudge_command/pretty_printers.py
onlinejudge_command/update_checking.py
onlinejudge_command/utils.py
onlinejudge_command/subcommand/__init__.py
onlinejudge_command/subcommand/download.py
onlinejudge_command/subcommand/generate_input.py
onlinejudge_command/subcommand/generate_output.py
onlinejudge_command/subcommand/login.py
onlinejudge_command/subcommand/submit.py
onlinejudge_command/subcommand/test.py
onlinejudge_command/subcommand/test_reactive.py
online_judge_tools-11.5.0.dist-info/LICENSE
online_judge_tools-11.5.0.dist-info/METADATA
online_judge_tools-11.5.0.dist-info/WHEEL
online_judge_tools-11.5.0.dist-info/entry_points.txt
online_judge_tools-11.5.0.dist-info/top_level.txt
online_judge_tools-11.5.0.dist-info/RECORD
