Metadata-Version: 2.1
Name: online-judge-tools
Version: 11.5.0
Summary: CLI tool to solve problems of competitive programming
Home-page: https://github.com/online-judge-tools/oj
Author: Kimiyuki Onaka
Author-email: kimiyuki95@gmail.com
License: MIT License
Platform: UNKNOWN
Classifier: Development Status :: 5 - Production/Stable
Classifier: Environment :: Console
Classifier: Intended Audience :: Developers
Classifier: License :: OSI Approved :: MIT License
Classifier: Operating System :: OS Independent
Classifier: Programming Language :: Python :: 3.5
Classifier: Programming Language :: Python :: 3.6
Classifier: Topic :: Internet :: WWW/HTTP
Classifier: Topic :: Software Development
Classifier: Topic :: Text Processing :: Markup :: HTML
Classifier: Topic :: Utilities
Requires-Python: >=3.6
Requires-Dist: online-judge-api-client (<11,>=10.9.0)
Requires-Dist: colorama (<1,>=0.3)
Requires-Dist: requests (<3,>=2)
Provides-Extra: dev
Requires-Dist: isort (==5.7.0) ; extra == 'dev'
Requires-Dist: mypy (==0.812) ; extra == 'dev'
Requires-Dist: pylint (==2.7.0) ; extra == 'dev'
Requires-Dist: yapf (==0.30.0) ; extra == 'dev'
Requires-Dist: pytest (<7,>=6.2.2) ; extra == 'dev'
Provides-Extra: selenium
Requires-Dist: selenium (>=3.141.0) ; extra == 'selenium'
